umf/__init__.py
umf/error.py
umf/metadata.py
umf/parse.py
umf_py-1.0.0.dist-info/licenses/LICENSE
umf_py-1.0.0.dist-info/METADATA
umf_py-1.0.0.dist-info/WHEEL
umf_py-1.0.0.dist-info/top_level.txt
umf_py-1.0.0.dist-info/RECORD
