Metadata-Version: 2.4
Name: umf.py
Version: 1.0.0
Summary: The Universal Metadata Format
Author: Self Hosting Media Group
License: MIT
Project-URL: Homepage, https://github.com/shmg-org/umf-python
Project-URL: Repository, https://github.com/shmg-org/umf-python.git
Classifier: Development Status :: 5 - Production/Stable
Classifier: Intended Audience :: Developers
Classifier: License :: OSI Approved :: MIT License
Classifier: Programming Language :: Python :: 3
Classifier: Programming Language :: Python :: 3.8
Classifier: Programming Language :: Python :: 3.9
Classifier: Programming Language :: Python :: 3.10
Classifier: Programming Language :: Python :: 3.11
Classifier: Programming Language :: Python :: 3.12
Requires-Python: >=3.8
License-File: LICENSE
Dynamic: license-file
